{
  "unversionedId": "api/classes/wrap_src.hoistfield",
  "id": "api/classes/wrap_src.hoistfield",
  "isDocsHomePage": false,
  "title": "wrap_src.hoistfield",
  "description": "Class: HoistField",
  "source": "@site/docs/api/classes/wrap_src.hoistfield.md",
  "slug": "/api/classes/wrap_src.hoistfield",
  "permalink": "/docs/api/classes/wrap_src.hoistfield",
  "editUrl": "https://github.com/ardatan/graphql-tools/edit/master/website/docs/api/classes/wrap_src.hoistfield.md",
  "version": "current",
  "sidebar": "someSidebar",
  "previous": {
    "title": "loaders_graphql_file_src.graphqlfileloader",
    "permalink": "/docs/api/classes/loaders_graphql_file_src.graphqlfileloader"
  },
  "next": {
    "title": "loaders_json_file_src.jsonfileloader",
    "permalink": "/docs/api/classes/loaders_json_file_src.jsonfileloader"
  }
}