{
  "unversionedId": "api/classes/wrap_src.extractfield",
  "id": "api/classes/wrap_src.extractfield",
  "isDocsHomePage": false,
  "title": "wrap_src.extractfield",
  "description": "Class: ExtractField",
  "source": "@site/docs/api/classes/wrap_src.extractfield.md",
  "slug": "/api/classes/wrap_src.extractfield",
  "permalink": "/docs/api/classes/wrap_src.extractfield",
  "editUrl": "https://github.com/ardatan/graphql-tools/edit/master/website/docs/api/classes/wrap_src.extractfield.md",
  "version": "current",
  "sidebar": "someSidebar",
  "previous": {
    "title": "delegate_src.expandabstracttypes",
    "permalink": "/docs/api/classes/delegate_src.expandabstracttypes"
  },
  "next": {
    "title": "wrap_src.filterinputobjectfields",
    "permalink": "/docs/api/classes/wrap_src.filterinputobjectfields"
  }
}